krieg/__init__.py
krieg/applications.py
krieg/exceptions.py
krieg/requests.py
krieg/responses.py
krieg/types.py
krieg-1.0.dist-info/LICENSE
krieg-1.0.dist-info/METADATA
krieg-1.0.dist-info/WHEEL
krieg-1.0.dist-info/RECORD
