Metadata-Version: 2.3
Name: krieg
Version: 1.0
Summary: Krieg framework, a lightweight asynchronous web framework built with Python, focused on simplicity and performance.
License: MIT
Author: pavelixo
Author-email: pavelixo@icloud.com
Requires-Python: >=3.10
Classifier: Framework :: AsyncIO
Classifier: Intended Audience :: Developers
Classifier: License :: OSI Approved :: MIT License
Classifier: Programming Language :: Python :: 3
Classifier: Programming Language :: Python :: 3.10
Classifier: Programming Language :: Python :: 3.11
Classifier: Programming Language :: Python :: 3.12
Classifier: Programming Language :: Python :: 3.13
Classifier: Topic :: Internet :: WWW/HTTP :: HTTP Servers
Classifier: Topic :: Software Development :: Libraries :: Python Modules
Requires-Dist: aiohttp (>=3.11.11)
Requires-Dist: pydantic (>=2.10.4)
